{
"meta":{"test_sets":[],"test_metrics":[],"learn_metrics":[{"best_value":"Min","name":"Logloss"}],"launch_mode":"Train","parameters":"","iteration_count":100,"learn_sets":["learn"],"name":"experiment"},
"iterations":[
{"learn":[0.6708894069],"iteration":0,"passed_time":0.003334418514,"remaining_time":0.3301074329},
{"learn":[0.6507457915],"iteration":1,"passed_time":0.006274400479,"remaining_time":0.3074456235},
{"learn":[0.6344461628],"iteration":2,"passed_time":0.009745303861,"remaining_time":0.3150981582},
{"learn":[0.6191097352],"iteration":3,"passed_time":0.01264652979,"remaining_time":0.3035167149},
{"learn":[0.605434459],"iteration":4,"passed_time":0.01538980957,"remaining_time":0.2924063818},
{"learn":[0.5934386171],"iteration":5,"passed_time":0.01825683052,"remaining_time":0.2860236782},
{"learn":[0.5822985145],"iteration":6,"passed_time":0.02337706565,"remaining_time":0.3105810151},
{"learn":[0.5735862927],"iteration":7,"passed_time":0.02608294363,"remaining_time":0.2999538517},
{"learn":[0.5652178847],"iteration":8,"passed_time":0.03060992964,"remaining_time":0.3095003997},
{"learn":[0.5570805503],"iteration":9,"passed_time":0.03923249506,"remaining_time":0.3530924555},
{"learn":[0.5492175216],"iteration":10,"passed_time":0.04108998805,"remaining_time":0.3324553579},
{"learn":[0.5408440333],"iteration":11,"passed_time":0.04271285565,"remaining_time":0.3132276081},
{"learn":[0.5352888189],"iteration":12,"passed_time":0.04445445683,"remaining_time":0.2975029034},
{"learn":[0.52835634],"iteration":13,"passed_time":0.04651067391,"remaining_time":0.2857084254},
{"learn":[0.5233976187],"iteration":14,"passed_time":0.04821753692,"remaining_time":0.2732327092},
{"learn":[0.5180625284],"iteration":15,"passed_time":0.04987766949,"remaining_time":0.2618577648},
{"learn":[0.5138304129],"iteration":16,"passed_time":0.05323431722,"remaining_time":0.2599087253},
{"learn":[0.5096800686],"iteration":17,"passed_time":0.05514503931,"remaining_time":0.2512162902},
{"learn":[0.5044470137],"iteration":18,"passed_time":0.05685971628,"remaining_time":0.2424019484},
{"learn":[0.500973963],"iteration":19,"passed_time":0.05849674198,"remaining_time":0.2339869679},
{"learn":[0.4973402238],"iteration":20,"passed_time":0.06053583416,"remaining_time":0.2277300428},
{"learn":[0.4942480077],"iteration":21,"passed_time":0.06229667062,"remaining_time":0.220870014},
{"learn":[0.4901940809],"iteration":22,"passed_time":0.06405486468,"remaining_time":0.214444547},
{"learn":[0.4877621245],"iteration":23,"passed_time":0.06554408328,"remaining_time":0.2075562637},
{"learn":[0.4849025627],"iteration":24,"passed_time":0.06836922803,"remaining_time":0.2051076841},
{"learn":[0.481527529],"iteration":25,"passed_time":0.07021950278,"remaining_time":0.1998555079},
{"learn":[0.4796763682],"iteration":26,"passed_time":0.07175117678,"remaining_time":0.1939939224},
{"learn":[0.4763865227],"iteration":27,"passed_time":0.07335895791,"remaining_time":0.1886373203},
{"learn":[0.474490369],"iteration":28,"passed_time":0.07486977933,"remaining_time":0.1833018735},
{"learn":[0.4732257942],"iteration":29,"passed_time":0.07634468649,"remaining_time":0.1781376018},
{"learn":[0.4719540085],"iteration":30,"passed_time":0.07797771554,"remaining_time":0.1735633023},
{"learn":[0.4699763934],"iteration":31,"passed_time":0.07956707888,"remaining_time":0.1690800426},
{"learn":[0.467554237],"iteration":32,"passed_time":0.08133087153,"remaining_time":0.1651263149},
{"learn":[0.4652136638],"iteration":33,"passed_time":0.08417670253,"remaining_time":0.1634018343},
{"learn":[0.4633844326],"iteration":34,"passed_time":0.08597814589,"remaining_time":0.1596736995},
{"learn":[0.4622484388],"iteration":35,"passed_time":0.08772621742,"remaining_time":0.1559577199},
{"learn":[0.4609050385],"iteration":36,"passed_time":0.0901573208,"remaining_time":0.1535111138},
{"learn":[0.458848955],"iteration":37,"passed_time":0.09174086614,"remaining_time":0.1496824658},
{"learn":[0.4573369211],"iteration":38,"passed_time":0.09334541622,"remaining_time":0.1460018049},
{"learn":[0.4557995512],"iteration":39,"passed_time":0.09492821129,"remaining_time":0.1423923169},
{"learn":[0.4542378605],"iteration":40,"passed_time":0.09784313643,"remaining_time":0.1407986597},
{"learn":[0.4534416916],"iteration":41,"passed_time":0.09963462241,"remaining_time":0.137590669},
{"learn":[0.4526329811],"iteration":42,"passed_time":0.1014286022,"remaining_time":0.134451868},
{"learn":[0.451564477],"iteration":43,"passed_time":0.1029412013,"remaining_time":0.1310160744},
{"learn":[0.4499797297],"iteration":44,"passed_time":0.1045143988,"remaining_time":0.1277398208},
{"learn":[0.4488684458],"iteration":45,"passed_time":0.1060372632,"remaining_time":0.1244785264},
{"learn":[0.4474051301],"iteration":46,"passed_time":0.1076165052,"remaining_time":0.1213547825},
{"learn":[0.4467263063],"iteration":47,"passed_time":0.109139983,"remaining_time":0.1182349816},
{"learn":[0.4456636222],"iteration":48,"passed_time":0.1106058754,"remaining_time":0.1151204009},
{"learn":[0.4446194765],"iteration":49,"passed_time":0.1136086663,"remaining_time":0.1136086663},
{"learn":[0.443715102],"iteration":50,"passed_time":0.1153083642,"remaining_time":0.1107864675},
{"learn":[0.4433134377],"iteration":51,"passed_time":0.1170842541,"remaining_time":0.108077773},
{"learn":[0.443028341],"iteration":52,"passed_time":0.1187371365,"remaining_time":0.1052951965},
{"learn":[0.4418029399],"iteration":53,"passed_time":0.1202687138,"remaining_time":0.1024511266},
{"learn":[0.4404380362],"iteration":54,"passed_time":0.1219025875,"remaining_time":0.09973848067},
{"learn":[0.4393081489],"iteration":55,"passed_time":0.1235311009,"remaining_time":0.09706015068},
{"learn":[0.4377037925],"iteration":56,"passed_time":0.1255815165,"remaining_time":0.09473693347},
{"learn":[0.4370143851],"iteration":57,"passed_time":0.1299675869,"remaining_time":0.09411445945},
{"learn":[0.4362258466],"iteration":58,"passed_time":0.1326588479,"remaining_time":0.09218665699},
{"learn":[0.4352837481],"iteration":59,"passed_time":0.1345740337,"remaining_time":0.08971602248},
{"learn":[0.4344738051],"iteration":60,"passed_time":0.1366949236,"remaining_time":0.08739511511},
{"learn":[0.432948483],"iteration":61,"passed_time":0.1382810901,"remaining_time":0.08475292621},
{"learn":[0.4314980152],"iteration":62,"passed_time":0.1399244647,"remaining_time":0.08217786021},
{"learn":[0.4305695743],"iteration":63,"passed_time":0.1425232404,"remaining_time":0.08016932271},
{"learn":[0.4290983171],"iteration":64,"passed_time":0.1442453892,"remaining_time":0.07767059419},
{"learn":[0.4273347593],"iteration":65,"passed_time":0.1457031278,"remaining_time":0.07505918706},
{"learn":[0.4265028638],"iteration":66,"passed_time":0.1473276729,"remaining_time":0.07256437619},
{"learn":[0.424806763],"iteration":67,"passed_time":0.1487642062,"remaining_time":0.07000668527},
{"learn":[0.4241517856],"iteration":68,"passed_time":0.150351373,"remaining_time":0.06754916759},
{"learn":[0.422804528],"iteration":69,"passed_time":0.1519753188,"remaining_time":0.0651322795},
{"learn":[0.421963097],"iteration":70,"passed_time":0.1535431489,"remaining_time":0.06271480731},
{"learn":[0.4213625379],"iteration":71,"passed_time":0.1550921967,"remaining_time":0.06031363206},
{"learn":[0.4201995572],"iteration":72,"passed_time":0.1584297366,"remaining_time":0.05859729983},
{"learn":[0.4192663731],"iteration":73,"passed_time":0.1601183104,"remaining_time":0.05625778473},
{"learn":[0.4181025545],"iteration":74,"passed_time":0.1616042944,"remaining_time":0.05386809813},
{"learn":[0.4172017497],"iteration":75,"passed_time":0.1630493164,"remaining_time":0.05148925782},
{"learn":[0.4162126751],"iteration":76,"passed_time":0.1644784935,"remaining_time":0.04912993961},
{"learn":[0.4155824697],"iteration":77,"passed_time":0.1659813157,"remaining_time":0.0468152429},
{"learn":[0.4146405673],"iteration":78,"passed_time":0.1674685006,"remaining_time":0.04451694321},
{"learn":[0.4139418898],"iteration":79,"passed_time":0.1688973474,"remaining_time":0.04222433685},
{"learn":[0.4134565807],"iteration":80,"passed_time":0.1706090116,"remaining_time":0.04001939777},
{"learn":[0.4129091051],"iteration":81,"passed_time":0.1730501502,"remaining_time":0.03798661833},
{"learn":[0.412056374],"iteration":82,"passed_time":0.1747086395,"remaining_time":0.03578369725},
{"learn":[0.4114555228],"iteration":83,"passed_time":0.1763242393,"remaining_time":0.03358556939},
{"learn":[0.411017055],"iteration":84,"passed_time":0.1778807118,"remaining_time":0.03139071385},
{"learn":[0.4099574178],"iteration":85,"passed_time":0.1792769555,"remaining_time":0.02918462067},
{"learn":[0.4091573546],"iteration":86,"passed_time":0.1809277217,"remaining_time":0.02703517681},
{"learn":[0.4087211162],"iteration":87,"passed_time":0.1823810343,"remaining_time":0.02487014104},
{"learn":[0.4075784188],"iteration":88,"passed_time":0.1839151219,"remaining_time":0.02273108248},
{"learn":[0.4066748405],"iteration":89,"passed_time":0.1866880485,"remaining_time":0.0207431165},
{"learn":[0.4060858151],"iteration":90,"passed_time":0.1883106117,"remaining_time":0.01862412643},
{"learn":[0.4052288499],"iteration":91,"passed_time":0.1898485638,"remaining_time":0.01650857076},
{"learn":[0.404798034],"iteration":92,"passed_time":0.1914354522,"remaining_time":0.01440912006},
{"learn":[0.4041303072],"iteration":93,"passed_time":0.1929989766,"remaining_time":0.01231908362},
{"learn":[0.4033469243],"iteration":94,"passed_time":0.1958993461,"remaining_time":0.0103104919},
{"learn":[0.4023322631],"iteration":95,"passed_time":0.1984305801,"remaining_time":0.008267940838},
{"learn":[0.4014907806],"iteration":96,"passed_time":0.202172127,"remaining_time":0.006252746195},
{"learn":[0.4007645263],"iteration":97,"passed_time":0.205697944,"remaining_time":0.004197917224},
{"learn":[0.3990441575],"iteration":98,"passed_time":0.2077007137,"remaining_time":0.002097987007},
{"learn":[0.3985569049],"iteration":99,"passed_time":0.2094373864,"remaining_time":0}
]}